{
  "$schema": "https://raw.githubusercontent.com/badlogic/pi-mono/main/packages/coding-agent/src/modes/interactive/theme/theme-schema.json",
  "name": "solarized-dark",
  "vars": {
    "red": 1,
    "green": 2,
    "yellow": 3,
    "blue": 4,
    "magenta": 5,
    "cyan": 6,
    "white": 7,
    "gray": 8,
    "base01": 10
  },
  "colors": {
    "accent": "cyan",
    "border": "blue",
    "borderAccent": "cyan",
    "borderMuted": "gray",
    "success": "green",
    "error": "red",
    "warning": "yellow",
    "muted": "base01",
    "dim": "gray",
    "text": "",
    "thinkingText": "base01",

    "selectedBg": 0,
    "userMessageBg": 0,
    "userMessageText": "",
    "customMessageBg": 0,
    "customMessageText": "",
    "customMessageLabel": "magenta",
    "toolPendingBg": 0,
    "toolSuccessBg": 0,
    "toolErrorBg": 0,
    "toolTitle": "",
    "toolOutput": "base01",

    "mdHeading": "yellow",
    "mdLink": "blue",
    "mdLinkUrl": "gray",
    "mdCode": "cyan",
    "mdCodeBlock": "green",
    "mdCodeBlockBorder": "gray",
    "mdQuote": "gray",
    "mdQuoteBorder": "gray",
    "mdHr": "gray",
    "mdListBullet": "cyan",

    "toolDiffAdded": "green",
    "toolDiffRemoved": "red",
    "toolDiffContext": "gray",

    "syntaxComment": "gray",
    "syntaxKeyword": "blue",
    "syntaxFunction": "yellow",
    "syntaxVariable": "cyan",
    "syntaxString": "green",
    "syntaxNumber": "magenta",
    "syntaxType": 6,
    "syntaxOperator": "",
    "syntaxPunctuation": "",

    "thinkingOff": "gray",
    "thinkingMinimal": "base01",
    "thinkingLow": 4,
    "thinkingMedium": "blue",
    "thinkingHigh": 5,
    "thinkingXhigh": "magenta",

    "bashMode": "green"
  },
  "export": {
    "pageBg": "#181818",
    "cardBg": "#1e1e1e",
    "infoBg": "#2a2a1e"
  }
}
